notekit/__init__.py
notekit/cli.py
notekit/extractor.py
notekit/notebooks/ANN/AND_NOT.py
notekit/notebooks/ANN/ART.py
notekit/notebooks/ANN/Activation_functions.py
notekit/notebooks/ANN/BAM.py
notekit/notebooks/ANN/Backpropagation_XOR.py
notekit/notebooks/ANN/Forward_Backwardpass.py
notekit/notebooks/ANN/Hopfield.py
notekit/notebooks/ANN/Logistic_regression.py
notekit/notebooks/ANN/MNIST.py
notekit/notebooks/ANN/Multiclass_classification.py
notekit/notebooks/ANN/Perceptron_decision_region.py
notekit/notebooks/ANN/Perceptron_even_odd_ascii.py
notekit/notebooks/ANN/cnn_object_detection_yolov8.py
notekit/notebooks/ANN/cnn_tensorflow.py
notekit/notebooks/ANN/custom_cnn_object_detection.py
notekit/notebooks/DS/AddNumbers.scala
notekit/notebooks/DS/DataVisualization1.ipynb
notekit/notebooks/DS/DataVisualization2.ipynb
notekit/notebooks/DS/DataVisualization3.ipynb
notekit/notebooks/DS/DataWrangling1.ipynb
notekit/notebooks/DS/DataWrangling2.ipynb
notekit/notebooks/DS/LinearRegression.ipynb
notekit/notebooks/DS/LogisticRegression.ipynb
notekit/notebooks/DS/NaiveBayes.ipynb
notekit/notebooks/DS/POS.ipynb
notekit/notebooks/DS/Statistics.ipynb
notekit/notebooks/DS/scala.txt
notekit-0.1.5.dist-info/METADATA
notekit-0.1.5.dist-info/WHEEL
notekit-0.1.5.dist-info/entry_points.txt
notekit-0.1.5.dist-info/top_level.txt
notekit-0.1.5.dist-info/RECORD
