Metadata-Version: 2.4
Name: notekit
Version: 0.1.5
Summary: A package to extract certain files
Author-email: Aditya Khalkar <khalkaraditya8@gmail.com>
Requires-Python: >=3.8
